MLEBot/__init__.py
MLEBot/enums.py
MLEBot/franchise.py
MLEBot/member.py
MLEBot/mle_bot.py
MLEBot/mle_commands.py
MLEBot/roles.py
MLEBot/sprocket_data_link.py
MLEBot/task_roster.py
MLEBot/task_sprocket.py
MLEBot/team.py
MLEBot/.idea/.gitignore
MLEBot/.idea/MLEBot.iml
MLEBot/.idea/material_theme_project_new.xml
MLEBot/.idea/misc.xml
MLEBot/.idea/modules.xml
MLEBot/.idea/vcs.xml
MLEBot/.idea/inspectionProfiles/Project_Default.xml
MLEBot/.idea/inspectionProfiles/profiles_settings.xml
MLEBot/team/html/TeamQuickInfo.css
MLEBot/team/html/TeamQuickInfo.html
MLEBot/team/html/TeamWeeklyStats.css
MLEBot/team/html/TeamWeeklyStats.html
MLEBot/team/imgs/ACADEMY.png
MLEBot/team/imgs/CHAMPION.png
MLEBot/team/imgs/FOUNDATION.png
MLEBot/team/imgs/MASTER.png
MLEBot/team/imgs/STAFF.png
mlebot-1.0.6.dist-info/METADATA
mlebot-1.0.6.dist-info/WHEEL
mlebot-1.0.6.dist-info/licenses/LICENSE
mlebot-1.0.6.dist-info/RECORD
