Metadata-Version: 2.3
Name: MLEBot
Version: 1.0.6
Summary: Minor League E-Sports Franchise Utility bot base-code.
Project-URL: Homepage, https://github.com/iroxusux/MLEBot
Project-URL: Issues, https://github.com/iroxusux/MLEBot/issues
Author-email: Brian LaFond <Brian.L.LaFond@gmail.com>
License: GNU GENERAL PUBLIC LICENSE
License-File: LICENSE
Keywords: MLE,api,bot,discord,minor league,python
Classifier: Development Status :: 4 - Beta
Classifier: Intended Audience :: Developers
Classifier: License :: OSI Approved :: GNU General Public License v3 (GPLv3)
Classifier: Programming Language :: Python :: 3.11
Classifier: Topic :: Software Development :: Build Tools
Requires-Python: >=3.11
Requires-Dist: discord-py
Requires-Dist: html2image
Requires-Dist: pydiscobot>=1.0.4
Requires-Dist: python-dotenv
Requires-Dist: requests
